PathCrypter-0.5.data/scripts/pathcrypter
PathCrypter-0.5.data/scripts/pathcrypter.bat
pathcrypter/__init__.py
pathcrypter/pathcrypter.py
pathcrypter/platform_files_installer.py
pathcrypter/static_data/__init__.py
pathcrypter/static_data/osx_workflows.zip
unit_tests/__init__.py
unit_tests/pathcrypter_ut.py
PathCrypter-0.5.dist-info/LICENSE
PathCrypter-0.5.dist-info/METADATA
PathCrypter-0.5.dist-info/WHEEL
PathCrypter-0.5.dist-info/top_level.txt
PathCrypter-0.5.dist-info/RECORD
