Metadata-Version: 2.1
Name: PathCrypter
Version: 0.5
Summary: Application to encrypt files and folder-names
Home-page: https://github.com/techandtools/pathcrypter
Author: Sven Baeck
Author-email: technologyandtooling@gmail.com
License: CISCO
Platform: UNKNOWN
Classifier: Programming Language :: Python :: 3
Classifier: Operating System :: OS Independent
Requires-Dist: pyAesCrypt
Requires-Dist: pycrypto (>=2.6.1)
